{"box_data": [{"position": {"minX": 45.0, "minY": -2.25, "maxX": 673.0, "maxY": 678.0}, "class_id": 3, "box_caption": "pitted_surface 0.112", "scores": {"class_score": 0.11224365234375}, "domain": "pixel"}, {"position": {"minX": 14.9375, "minY": 30.75, "maxX": 146.25, "maxY": 677.0}, "class_id": 5, "box_caption": "scratches 0.042", "scores": {"class_score": 0.042266845703125}, "domain": "pixel"}, {"position": {"minX": 2.5, "minY": 4.0, "maxX": 412.75, "maxY": 680.0}, "class_id": 3, "box_caption": "pitted_surface 0.033", "scores": {"class_score": 0.03289794921875}, "domain": "pixel"}, {"position": {"minX": 10.1875, "minY": 18.5, "maxX": 147.75, "maxY": 671.5}, "class_id": 3, "box_caption": "pitted_surface 0.027", "scores": {"class_score": 0.0269012451171875}, "domain": "pixel"}, {"position": {"minX": 253.0, "minY": 37.75, "maxX": 648.5, "maxY": 667.0}, "class_id": 3, "box_caption": "pitted_surface 0.020", "scores": {"class_score": 0.0195159912109375}, "domain": "pixel"}, {"position": {"minX": 445.5, "minY": 7.0, "maxX": 660.5, "maxY": 669.0}, "class_id": 3, "box_caption": "pitted_surface 0.013", "scores": {"class_score": 0.013153076171875}, "domain": "pixel"}, {"position": {"minX": 10.1875, "minY": 18.5, "maxX": 147.75, "maxY": 671.5}, "class_id": 1, "box_caption": "inclusion 0.012", "scores": {"class_score": 0.0120849609375}, "domain": "pixel"}, {"position": {"minX": 22.25, "minY": 27.5, "maxX": 266.25, "maxY": 675.5}, "class_id": 3, "box_caption": "pitted_surface 0.010", "scores": {"class_score": 0.0104217529296875}, "domain": "pixel"}, {"position": {"minX": 8.4375, "minY": 8.25, "maxX": 217.5, "maxY": 661.0}, "class_id": 5, "box_caption": "scratches 0.008", "scores": {"class_score": 0.0082550048828125}, "domain": "pixel"}, {"position": {"minX": 573.0, "minY": -5.75, "maxX": 668.0, "maxY": 678.0}, "class_id": 3, "box_caption": "pitted_surface 0.005", "scores": {"class_score": 0.005329132080078125}, "domain": "pixel"}, {"position": {"minX": 41.4375, "minY": 161.625, "maxX": 199.75, "maxY": 624.5}, "class_id": 5, "box_caption": "scratches 0.004", "scores": {"class_score": 0.00429534912109375}, "domain": "pixel"}, {"position": {"minX": 1.5625, "minY": 17.625, "maxX": 91.6875, "maxY": 201.0}, "class_id": 1, "box_caption": "inclusion 0.004", "scores": {"class_score": 0.004161834716796875}, "domain": "pixel"}, {"position": {"minX": 6.40625, "minY": 27.875, "maxX": 103.75, "maxY": 389.5}, "class_id": 1, "box_caption": "inclusion 0.004", "scores": {"class_score": 0.003993988037109375}, "domain": "pixel"}, {"position": {"minX": 573.0, "minY": -5.75, "maxX": 668.0, "maxY": 678.0}, "class_id": 5, "box_caption": "scratches 0.004", "scores": {"class_score": 0.0038242340087890625}, "domain": "pixel"}, {"position": {"minX": 10.625, "minY": 17.25, "maxX": 109.0, "maxY": 671.0}, "class_id": 2, "box_caption": "patches 0.003", "scores": {"class_score": 0.0030364990234375}, "domain": "pixel"}, {"position": {"minX": 26.0, "minY": 21.25, "maxX": 317.5, "maxY": 682.0}, "class_id": 5, "box_caption": "scratches 0.003", "scores": {"class_score": 0.0027942657470703125}, "domain": "pixel"}, {"position": {"minX": 7.125, "minY": 21.8125, "maxX": 70.625, "maxY": 153.75}, "class_id": 1, "box_caption": "inclusion 0.003", "scores": {"class_score": 0.0027904510498046875}, "domain": "pixel"}, {"position": {"minX": 54.75, "minY": 3.75, "maxX": 666.0, "maxY": 663.0}, "class_id": 0, "box_caption": "crazing 0.002", "scores": {"class_score": 0.002300262451171875}, "domain": "pixel"}, {"position": {"minX": 11.65625, "minY": 283.0, "maxX": 106.875, "maxY": 662.0}, "class_id": 5, "box_caption": "scratches 0.002", "scores": {"class_score": 0.00225830078125}, "domain": "pixel"}, {"position": {"minX": 14.625, "minY": 3.25, "maxX": 273.0, "maxY": 665.0}, "class_id": 1, "box_caption": "inclusion 0.002", "scores": {"class_score": 0.0019683837890625}, "domain": "pixel"}, {"position": {"minX": 57.25, "minY": 2.4375, "maxX": 670.0, "maxY": 217.25}, "class_id": 0, "box_caption": "crazing 0.002", "scores": {"class_score": 0.0018739700317382812}, "domain": "pixel"}, {"position": {"minX": 623.0, "minY": -4.125, "maxX": 671.0, "maxY": 310.5}, "class_id": 5, "box_caption": "scratches 0.002", "scores": {"class_score": 0.0018291473388671875}, "domain": "pixel"}, {"position": {"minX": 594.5, "minY": 32.0, "maxX": 669.5, "maxY": 500.0}, "class_id": 5, "box_caption": "scratches 0.002", "scores": {"class_score": 0.001819610595703125}, "domain": "pixel"}, {"position": {"minX": 7.875, "minY": 15.4375, "maxX": 138.875, "maxY": 202.25}, "class_id": 1, "box_caption": "inclusion 0.002", "scores": {"class_score": 0.0016412734985351562}, "domain": "pixel"}, {"position": {"minX": 27.75, "minY": 71.625, "maxX": 181.625, "maxY": 524.0}, "class_id": 5, "box_caption": "scratches 0.002", "scores": {"class_score": 0.0016126632690429688}, "domain": "pixel"}, {"position": {"minX": 58.75, "minY": -4.75, "maxX": 667.0, "maxY": 351.75}, "class_id": 0, "box_caption": "crazing 0.002", "scores": {"class_score": 0.0015554428100585938}, "domain": "pixel"}, {"position": {"minX": 68.75, "minY": 3.875, "maxX": 657.0, "maxY": 410.5}, "class_id": 3, "box_caption": "pitted_surface 0.002", "scores": {"class_score": 0.0015392303466796875}, "domain": "pixel"}, {"position": {"minX": -3.640625, "minY": 20.875, "maxX": 59.5, "maxY": 265.5}, "class_id": 1, "box_caption": "inclusion 0.002", "scores": {"class_score": 0.0015316009521484375}, "domain": "pixel"}, {"position": {"minX": -1.125, "minY": 14.75, "maxX": 166.125, "maxY": 654.0}, "class_id": 2, "box_caption": "patches 0.002", "scores": {"class_score": 0.001529693603515625}, "domain": "pixel"}, {"position": {"minX": 33.625, "minY": 541.5, "maxX": 209.125, "maxY": 655.5}, "class_id": 5, "box_caption": "scratches 0.001", "scores": {"class_score": 0.0014896392822265625}, "domain": "pixel"}, {"position": {"minX": 22.75, "minY": 258.0, "maxX": 640.0, "maxY": 667.5}, "class_id": 3, "box_caption": "pitted_surface 0.001", "scores": {"class_score": 0.0014829635620117188}, "domain": "pixel"}, {"position": {"minX": 18.4375, "minY": 503.75, "maxX": 145.0, "maxY": 659.5}, "class_id": 5, "box_caption": "scratches 0.001", "scores": {"class_score": 0.0014524459838867188}, "domain": "pixel"}, {"position": {"minX": 22.5, "minY": 286.5, "maxX": 185.75, "maxY": 659.5}, "class_id": 5, "box_caption": "scratches 0.001", "scores": {"class_score": 0.0012292861938476562}, "domain": "pixel"}, {"position": {"minX": 12.5, "minY": 246.875, "maxX": 654.0, "maxY": 663.0}, "class_id": 0, "box_caption": "crazing 0.001", "scores": {"class_score": 0.0012197494506835938}, "domain": "pixel"}, {"position": {"minX": 6.25, "minY": -0.625, "maxX": 134.875, "maxY": 468.5}, "class_id": 5, "box_caption": "scratches 0.001", "scores": {"class_score": 0.0011844635009765625}, "domain": "pixel"}, {"position": {"minX": 57.25, "minY": 2.4375, "maxX": 670.0, "maxY": 217.25}, "class_id": 3, "box_caption": "pitted_surface 0.001", "scores": {"class_score": 0.0011358261108398438}, "domain": "pixel"}, {"position": {"minX": -1.59375, "minY": 21.625, "maxX": 67.75, "maxY": 397.5}, "class_id": 1, "box_caption": "inclusion 0.001", "scores": {"class_score": 0.0010824203491210938}, "domain": "pixel"}, {"position": {"minX": 1.5, "minY": 4.25, "maxX": 476.5, "maxY": 676.0}, "class_id": 5, "box_caption": "scratches 0.001", "scores": {"class_score": 0.0010738372802734375}, "domain": "pixel"}, {"position": {"minX": 600.5, "minY": 135.125, "maxX": 665.5, "maxY": 589.0}, "class_id": 5, "box_caption": "scratches 0.001", "scores": {"class_score": 0.0010318756103515625}, "domain": "pixel"}, {"position": {"minX": 307.0, "minY": 155.375, "maxX": 445.0, "maxY": 665.5}, "class_id": 5, "box_caption": "scratches 0.001", "scores": {"class_score": 0.0010089874267578125}, "domain": "pixel"}], "class_labels": {"0": "crazing", "1": "inclusion", "2": "patches", "3": "pitted_surface", "4": "rolled-in_scale", "5": "scratches"}}