{"box_data": [{"position": {"minX": 26.5, "minY": 34.0, "maxX": 643.0, "maxY": 650.5}, "class_id": 3, "box_caption": "pitted_surface 0.346", "scores": {"class_score": 0.345947265625}, "domain": "pixel"}, {"position": {"minX": 401.0, "minY": 27.0, "maxX": 651.0, "maxY": 639.5}, "class_id": 3, "box_caption": "pitted_surface 0.033", "scores": {"class_score": 0.033355712890625}, "domain": "pixel"}, {"position": {"minX": 2.875, "minY": 114.75, "maxX": 238.125, "maxY": 645.0}, "class_id": 3, "box_caption": "pitted_surface 0.025", "scores": {"class_score": 0.024658203125}, "domain": "pixel"}, {"position": {"minX": 35.0, "minY": 27.5, "maxX": 396.0, "maxY": 650.0}, "class_id": 3, "box_caption": "pitted_surface 0.018", "scores": {"class_score": 0.017822265625}, "domain": "pixel"}, {"position": {"minX": 508.0, "minY": 22.75, "maxX": 657.0, "maxY": 644.0}, "class_id": 3, "box_caption": "pitted_surface 0.010", "scores": {"class_score": 0.01009368896484375}, "domain": "pixel"}, {"position": {"minX": 458.0, "minY": 142.75, "maxX": 665.0, "maxY": 680.0}, "class_id": 3, "box_caption": "pitted_surface 0.009", "scores": {"class_score": 0.00933074951171875}, "domain": "pixel"}, {"position": {"minX": 345.75, "minY": 123.0, "maxX": 591.0, "maxY": 672.0}, "class_id": 3, "box_caption": "pitted_surface 0.008", "scores": {"class_score": 0.0078887939453125}, "domain": "pixel"}, {"position": {"minX": 569.0, "minY": 108.25, "maxX": 660.0, "maxY": 651.0}, "class_id": 3, "box_caption": "pitted_surface 0.006", "scores": {"class_score": 0.005893707275390625}, "domain": "pixel"}, {"position": {"minX": 26.5, "minY": 34.0, "maxX": 643.0, "maxY": 650.5}, "class_id": 5, "box_caption": "scratches 0.006", "scores": {"class_score": 0.00555419921875}, "domain": "pixel"}, {"position": {"minX": 62.0625, "minY": 77.5, "maxX": 303.75, "maxY": 621.5}, "class_id": 3, "box_caption": "pitted_surface 0.005", "scores": {"class_score": 0.004611968994140625}, "domain": "pixel"}, {"position": {"minX": 2.875, "minY": 114.75, "maxX": 238.125, "maxY": 645.0}, "class_id": 1, "box_caption": "inclusion 0.004", "scores": {"class_score": 0.004222869873046875}, "domain": "pixel"}, {"position": {"minX": 265.0, "minY": 104.5, "maxX": 514.0, "maxY": 660.5}, "class_id": 3, "box_caption": "pitted_surface 0.004", "scores": {"class_score": 0.0037593841552734375}, "domain": "pixel"}, {"position": {"minX": 188.625, "minY": 58.5, "maxX": 435.5, "maxY": 610.5}, "class_id": 3, "box_caption": "pitted_surface 0.003", "scores": {"class_score": 0.0034618377685546875}, "domain": "pixel"}, {"position": {"minX": 257.0, "minY": 55.0, "maxX": 649.0, "maxY": 655.5}, "class_id": 3, "box_caption": "pitted_surface 0.003", "scores": {"class_score": 0.0034427642822265625}, "domain": "pixel"}, {"position": {"minX": 2.875, "minY": 114.75, "maxX": 238.125, "maxY": 645.0}, "class_id": 2, "box_caption": "patches 0.003", "scores": {"class_score": 0.0031909942626953125}, "domain": "pixel"}, {"position": {"minX": 459.5, "minY": 12.0, "maxX": 655.5, "maxY": 649.5}, "class_id": 1, "box_caption": "inclusion 0.003", "scores": {"class_score": 0.0026683807373046875}, "domain": "pixel"}, {"position": {"minX": 15.8125, "minY": 14.125, "maxX": 226.75, "maxY": 520.0}, "class_id": 3, "box_caption": "pitted_surface 0.003", "scores": {"class_score": 0.0026149749755859375}, "domain": "pixel"}, {"position": {"minX": 13.5625, "minY": 121.5, "maxX": 104.0625, "maxY": 639.0}, "class_id": 3, "box_caption": "pitted_surface 0.002", "scores": {"class_score": 0.002292633056640625}, "domain": "pixel"}, {"position": {"minX": 9.0, "minY": 21.25, "maxX": 657.0, "maxY": 650.0}, "class_id": 0, "box_caption": "crazing 0.002", "scores": {"class_score": 0.0022716522216796875}, "domain": "pixel"}, {"position": {"minX": 137.5, "minY": 104.0, "maxX": 386.0, "maxY": 657.5}, "class_id": 3, "box_caption": "pitted_surface 0.002", "scores": {"class_score": 0.002254486083984375}, "domain": "pixel"}, {"position": {"minX": 9.0, "minY": 21.25, "maxX": 657.0, "maxY": 650.0}, "class_id": 1, "box_caption": "inclusion 0.002", "scores": {"class_score": 0.0018644332885742188}, "domain": "pixel"}, {"position": {"minX": -3.0, "minY": 24.0, "maxX": 614.0, "maxY": 646.0}, "class_id": 2, "box_caption": "patches 0.002", "scores": {"class_score": 0.0016412734985351562}, "domain": "pixel"}, {"position": {"minX": 88.8125, "minY": 77.25, "maxX": 339.0, "maxY": 622.0}, "class_id": 1, "box_caption": "inclusion 0.002", "scores": {"class_score": 0.0015087127685546875}, "domain": "pixel"}, {"position": {"minX": 155.25, "minY": 163.375, "maxX": 641.0, "maxY": 514.0}, "class_id": 3, "box_caption": "pitted_surface 0.001", "scores": {"class_score": 0.0013599395751953125}, "domain": "pixel"}, {"position": {"minX": 324.0, "minY": 16.75, "maxX": 656.5, "maxY": 648.0}, "class_id": 1, "box_caption": "inclusion 0.001", "scores": {"class_score": 0.0012760162353515625}, "domain": "pixel"}, {"position": {"minX": 597.0, "minY": 75.75, "maxX": 665.0, "maxY": 620.0}, "class_id": 3, "box_caption": "pitted_surface 0.001", "scores": {"class_score": 0.0012226104736328125}, "domain": "pixel"}, {"position": {"minX": 425.5, "minY": 121.25, "maxX": 668.5, "maxY": 673.0}, "class_id": 5, "box_caption": "scratches 0.001", "scores": {"class_score": 0.00116729736328125}, "domain": "pixel"}, {"position": {"minX": 17.5, "minY": 126.625, "maxX": 126.375, "maxY": 634.0}, "class_id": 1, "box_caption": "inclusion 0.001", "scores": {"class_score": 0.0011577606201171875}, "domain": "pixel"}, {"position": {"minX": 16.65625, "minY": 40.25, "maxX": 129.375, "maxY": 563.0}, "class_id": 3, "box_caption": "pitted_surface 0.001", "scores": {"class_score": 0.0010786056518554688}, "domain": "pixel"}, {"position": {"minX": 177.0, "minY": 18.15625, "maxX": 216.5, "maxY": 102.25}, "class_id": 1, "box_caption": "inclusion 0.001", "scores": {"class_score": 0.0010700225830078125}, "domain": "pixel"}, {"position": {"minX": 317.5, "minY": 32.5, "maxX": 559.0, "maxY": 574.0}, "class_id": 3, "box_caption": "pitted_surface 0.001", "scores": {"class_score": 0.0010519027709960938}, "domain": "pixel"}], "class_labels": {"0": "crazing", "1": "inclusion", "2": "patches", "3": "pitted_surface", "4": "rolled-in_scale", "5": "scratches"}}